jsz/rapidbuild/__init__.py
jsz/rapidbuild/base.py
jsz/rapidbuild/compiler_base.py
jsz/rapidbuild/compiler_llvm.py
jsz/rapidbuild/compiler_msvc.py
jsz/rapidbuild/conan.py
jsz/rapidbuild/fastbuild.py
jsz/rapidbuild/graph.py
jsz/rapidbuild/librarian_base.py
jsz/rapidbuild/librarian_llvm.py
jsz/rapidbuild/librarian_msvc.py
jsz/rapidbuild/linker_base.py
jsz/rapidbuild/linker_llvm.py
jsz/rapidbuild/linker_msvc.py
jsz/rapidbuild/target_graph.py
jsz/rapidbuild/toolchain.py
jsz/rapidbuild/workspace.py
jsz/rapidbuild/workspace_def.py
jsz/rapidbuild/conan_generator/__init__.py
jsz/rapidbuild/conan_generator/conanfile.py
jsz.rapidbuild-0.7.1.dist-info/LICENSE.txt
jsz.rapidbuild-0.7.1.dist-info/METADATA
jsz.rapidbuild-0.7.1.dist-info/WHEEL
jsz.rapidbuild-0.7.1.dist-info/top_level.txt
jsz.rapidbuild-0.7.1.dist-info/RECORD
